[{"section":"МАТЕМАТИКА В ІТ","subsection":"Застосування методів математичного аналізу, аналітичної геометрії, лінійної алгебри в ІТ","subsubsection":"Системи лінійних алгебраїчних рівнянь, умови їх розв’язності. Чисельні методи їх розв’язання","question":"Що таке чисельний метод розв’язання систем лінійних рівнянь?","options":["Метод, який використовує наближені значення для знаходження розв'язків","Метод, який використовує графічні методи для знаходження розв'язків","Метод, який використовує аналітичні вирази для знаходження розв'язків","Метод, який використовує інтеграли для знаходження розв'язків"],"correctAnswer":"A"},{"section":"МАТЕМАТИКА В ІТ","subsection":"Застосування методів математичного аналізу, аналітичної геометрії, лінійної алгебри в ІТ","subsubsection":"Матриці та дії з матрицями. Визначники. Обернена матриця","question":"Що таке обернена матриця?","options":["Матриця, яку можна отримати шляхом множення початкової матриці на скаляр","Матриця, яку можна отримати шляхом транспонування початкової матриці","Матриця, яка при множенні на початкову матрицю дає одиничну матрицю","Матриця, яку можна отримати шляхом додавання одиничної матриці до початкової"],"correctAnswer":"C"}]
