{
  "questions": [
    {
      "section": 1,
      "subsection": 1,
      "subsubsection": 3,
      "question": "Що таке кортеж?",
      "options": [
        "Упорядкована колекція елементів різних типів",
        "Колекція унікальних елементів одного типу",
        "Колекція пар ключ-значення",
        "Динамічно змінювана колекція елементів"
      ],
      "correctOption": "Упорядкована колекція елементів різних типів"
    },
    {
      "section": 1,
      "subsection": 1,
      "subsubsection": 3,
      "question": "Яка основна відмінність між одно- та двобічнозв'язними списками?",
      "options": [
        "Однозв'язний список має посилання тільки на наступний елемент, а двобічнозв'язний - на наступний і попередній",
        "Однозв'язний список має унікальні елементи, а двобічнозв'язний - ні",
        "Однозв'язний список є статичним, а двобічнозв'язний - динамічним",
        "Однозв'язний список дозволяє доступ до елементів за індексом, а двобічнозв'язний - ні"
      ],
      "correctOption": "Однозв'язний список має посилання тільки на наступний елемент, а двобічнозв'язний - на наступний і попередній"
    },
    {
      "section": 1,
      "subsection": 1,
      "subsubsection": 3,
      "question": "Яка з операцій у множині зазвичай має складність O(1)?",
      "options": [
        "Вставка елемента",
        "Видалення елемента",
        "Пошук елемента",
        "Всі перелічені"
      ],
      "correctOption": "Всі перелічені"
    },
    {
      "section": 1,
      "subsection": 1,
      "subsubsection": 3,
      "question": "Яка з наведених структур даних дозволяє зберігати пари ключ-значення?",
      "options": [
        "Словник",
        "Однозв'язний список",
        "Кортеж",
        "Множина"
      ],
      "correctOption": "Словник"
    },
    {
      "section": 1,
      "subsection": 1,
      "subsubsection": 3,
      "question": "Яка з операцій у словнику зазвичай має складність O(1)?",
      "options": [
        "Вставка елемента",
        "Видалення елемента",
        "Пошук елемента за ключем",
        "Всі перелічені"
      ],
      "correctOption": "Всі перелічені"
    },
    {
      "section": 1,
      "subsection": 1,
      "subsubsection": 3,
      "question": "Яка структура даних має складність вставки O(1) у середньому випадку?",
      "options": [
        "Однозв'язний список",
        "Двобічнозв'язний список",
        "Множина",
        "Словник"
      ],
      "correctOption": "Множина"
    },
    {
      "section": 1,
      "subsection": 1,
      "subsubsection": 3,
      "question": "Що таке одно- та двобічнозв'язні списки?",
      "options": [
        "Структури даних, що представляють собою послідовності елементів, де кожен елемент пов'язаний з наступним (і попереднім у двобічнозв'язному списку)",
        "Структури даних, що зберігають пари ключ-значення",
        "Структури даних, що зберігають унікальні елементи",
        "Структури даних, що мають фіксовану довжину"
      ],
      "correctOption": "Структури даних, що представляють собою послідовності елементів, де кожен елемент пов'язаний з наступним (і попереднім у двобічнозв'язному списку)"
    },
    {
      "section": 1,
      "subsection": 1,
      "subsubsection": 3,
      "question": "Яка структура даних зазвичай використовує хеш-функції для організації даних?",
      "options": [
        "Множина",
        "Словник",
        "Кортеж",
        "Однозв'язний список"
      ],
      "correctOption": "Словник"
    },
    {
      "section": 1,
      "subsection": 1,
      "subsubsection": 3,
      "question": "Яка складність операції доступу до елемента за індексом у однозв'язному списку?",
      "options": [
        "O(1)",
        "O(n)",
        "O(log n)",
        "O(n log n)"
      ],
      "correctOption": "O(n)"
    },
    {
      "section": 1,
      "subsection": 1,
      "subsubsection": 3,
      "question": "Яка складність операції видалення елемента у двобічнозв'язному списку?",
      "options": [
        "O(1)",
        "O(n)",
        "O(log n)",
        "O(n log n)"
      ],
      "correctOption": "O(1)"
    }
  ]
}
